toolbox_llamaindex/__init__.py
toolbox_llamaindex/async_client.py
toolbox_llamaindex/async_tools.py
toolbox_llamaindex/client.py
toolbox_llamaindex/py.typed
toolbox_llamaindex/tools.py
toolbox_llamaindex/version.py
toolbox_llamaindex-0.5.7.dist-info/METADATA
toolbox_llamaindex-0.5.7.dist-info/WHEEL
toolbox_llamaindex-0.5.7.dist-info/top_level.txt
toolbox_llamaindex-0.5.7.dist-info/RECORD
