Metadata-Version: 2.4
Name: toolbox-llamaindex
Version: 0.5.7
Summary: Python SDK for interacting with the Toolbox service with LlamaIndex
Author-email: Google LLC <googleapis-packages@google.com>
Project-URL: Homepage, https://github.com/googleapis/mcp-toolbox-sdk-python/blob/main/packages/toolbox-llamaindex
Project-URL: Repository, https://github.com/googleapis/mcp-toolbox-sdk-python.git
Project-URL: Bug Tracker, https://github.com/googleapis/mcp-toolbox-sdk-python/issues
Project-URL: Changelog, https://github.com/googleapis/mcp-toolbox-sdk-python/blob/main/packages/toolbox-llamaindex/CHANGELOG.md
Classifier: Intended Audience :: Developers
Classifier: License :: OSI Approved :: Apache Software License
Classifier: Programming Language :: Python
Classifier: Programming Language :: Python :: 3
Classifier: Programming Language :: Python :: 3.10
Classifier: Programming Language :: Python :: 3.11
Classifier: Programming Language :: Python :: 3.12
Classifier: Programming Language :: Python :: 3.13
Classifier: Programming Language :: Python :: 3.14
Requires-Python: >=3.10
Requires-Dist: toolbox-core==0.5.7
Requires-Dist: llama-index-core<1.0.0,>=0.12.0
Requires-Dist: PyYAML<7.0.0,>=6.0.1
Requires-Dist: pydantic<3.0.0,>=2.8.0
Requires-Dist: aiohttp<4.0.0,>=3.8.6
Requires-Dist: deprecated<2.0.0,>=1.2.10
Provides-Extra: test
Requires-Dist: black[jupyter]==25.12.0; extra == "test"
Requires-Dist: isort==7.0.0; extra == "test"
Requires-Dist: mypy==1.19.1; extra == "test"
Requires-Dist: pytest-asyncio==1.3.0; extra == "test"
Requires-Dist: pytest==9.0.2; extra == "test"
Requires-Dist: pytest-cov==7.0.0; extra == "test"
Requires-Dist: Pillow==12.1.0; python_version >= "3.10" and extra == "test"
Requires-Dist: google-cloud-secret-manager==2.26.0; extra == "test"
Requires-Dist: google-cloud-storage==3.7.0; extra == "test"
